LICENSE.txt
MANIFEST.in
README.md
setup.py
YAMLIndexer.egg-info/PKG-INFO
YAMLIndexer.egg-info/SOURCES.txt
YAMLIndexer.egg-info/dependency_links.txt
YAMLIndexer.egg-info/requires.txt
YAMLIndexer.egg-info/top_level.txt
yamlindexer/__init__.py
yamlindexer/cache.py
yamlindexer/core.py
yamlindexer/utils.py
yamlindexer/version.py