Metadata-Version: 2.1
Name: YAMLIndexer
Version: 0.1.1
Summary: Python package to index YAML files for quicker searches
Home-page: https://github.com/ruizink/python-yamlindexer
Author: Mario Santos
Author-email: mario.rf.santos@gmail.com
License: MIT
Platform: UNKNOWN
Classifier: Development Status :: 3 - Alpha
Classifier: Environment :: Console
Classifier: Intended Audience :: Developers
Classifier: License :: OSI Approved :: MIT License
Classifier: Natural Language :: English
Classifier: Programming Language :: Python :: 3
Classifier: Topic :: Software Development :: Libraries :: Python Modules
Requires-Python: >=3
License-File: LICENSE.txt
